{
  "depto": "ORURO",
  "prov": "CARANGAS",
  "mun": "CHOQUE COTA",
  "poblacion": {
    "edades": {
      "edad0a3": {
        "hombre": 72,
        "mujer": 69
      },
      "edad4a5": {
        "hombre": 48,
        "mujer": 26
      },
      "edad6a19": {
        "hombre": 270,
        "mujer": 238
      },
      "edad20a39": {
        "hombre": 268,
        "mujer": 254
      },
      "edad40a59": {
        "hombre": 171,
        "mujer": 174
      },
      "edad60oMas": {
        "hombre": 123,
        "mujer": 137
      }
    },
    "mayorDeEdad": {
      "hombre": 593,
      "mujer": 596
    },
    "vivienda": {
      "particular": {
        "hombre": 949,
        "mujer": 895
      },
      "colectiva": {
        "hombre": 2,
        "mujer": 2
      },
      "movil": {
        "hombre": 1,
        "mujer": 1
      },
      "sinVivienda": {
        "hombre": 0,
        "mujer": 0
      }
    },
    "conCi": {
      "hombre": 809,
      "mujer": 772
    },
    "salud": {
      "caja": {
        "hombre": 145,
        "mujer": 116
      },
      "seguroPrivado": {
        "hombre": 53,
        "mujer": 37
      },
      "establecimientoPublico": {
        "hombre": 752,
        "mujer": 725
      },
      "establecimientoPrivado": {
        "hombre": 65,
        "mujer": 51
      },
      "medicoTradicional": {
        "hombre": 525,
        "mujer": 497
      },
      "solucionCasera": {
        "hombre": 621,
        "mujer": 599
      },
      "farmacia": {
        "hombre": 500,
        "mujer": 455
      }
    },
    "ocupacion": {
      "agricultura": {
        "hombre": 280,
        "mujer": 285
      },
      "mineria": {
        "hombre": 0,
        "mujer": 2
      },
      "manufactura": {
        "hombre": 28,
        "mujer": 21
      },
      "electricidad": {
        "hombre": 0,
        "mujer": 0
      },
      "construccion": {
        "hombre": 50,
        "mujer": 2
      },
      "comercio": {
        "hombre": 61,
        "mujer": 57
      },
      "otrosServicios": {
        "hombre": 76,
        "mujer": 60
      },
      "sinEspecificar": {
        "hombre": 21,
        "mujer": 8
      },
      "descripcionIncompleta": {
        "hombre": 7,
        "mujer": 5
      }
    },
    "tipoEmpleo": {
      "obrero": {
        "hombre": 101,
        "mujer": 44
      },
      "trabajadorDelHogar": {
        "hombre": 0,
        "mujer": 6
      },
      "cuentaPropia": {
        "hombre": 345,
        "mujer": 299
      },
      "empleador": {
        "hombre": 15,
        "mujer": 9
      },
      "aprendiz": {
        "hombre": 13,
        "mujer": 20
      },
      "servicios": {
        "hombre": 0,
        "mujer": 0
      },
      "sinEspecificar": {
        "hombre": 49,
        "mujer": 62
      }
    }
  },
  "vivienda": {
    "particular": 1006,
    "colectiva": 3,
    "energia": {
      "tiene": 253,
      "noTiene": 263
    },
    "cocina": {
      "garrafa": 86,
      "gasDomiciliario": 0,
      "lena": 413,
      "otro": 1,
      "noCocina": 16
    },
    "agua": {
      "caneria": 76,
      "pilaPublica": 19,
      "carroRepartidor": 0,
      "pozo": 312,
      "rio": 105,
      "otro": 4
    },
    "desague": {
      "alcantarilla": 0,
      "camara": 12,
      "pozo": 78,
      "calle": 1,
      "rio": 2,
      "lago": 0
    },
    "basura": {
      "contenedor": 22,
      "carro": 15,
      "calle": 23,
      "rio": 75,
      "quema": 315,
      "entierro": 45,
      "otro": 21
    },
    "tics": {
      "radio": 391,
      "television": 37,
      "computador": 10,
      "internet": 1,
      "celular": 133
    }
  }
}