{
  "depto": "LA PAZ",
  "prov": "INQUISIVI",
  "mun": "ICHOCA",
  "poblacion": {
    "edades": {
      "edad0a3": {
        "hombre": 354,
        "mujer": 331
      },
      "edad4a5": {
        "hombre": 180,
        "mujer": 165
      },
      "edad6a19": {
        "hombre": 1295,
        "mujer": 1242
      },
      "edad20a39": {
        "hombre": 1063,
        "mujer": 917
      },
      "edad40a59": {
        "hombre": 769,
        "mujer": 655
      },
      "edad60oMas": {
        "hombre": 501,
        "mujer": 441
      }
    },
    "mayorDeEdad": {
      "hombre": 2499,
      "mujer": 2168
    },
    "vivienda": {
      "particular": {
        "hombre": 4046,
        "mujer": 3711
      },
      "colectiva": {
        "hombre": 109,
        "mujer": 38
      },
      "movil": {
        "hombre": 7,
        "mujer": 2
      },
      "sinVivienda": {
        "hombre": 0,
        "mujer": 0
      }
    },
    "conCi": {
      "hombre": 3516,
      "mujer": 3116
    },
    "salud": {
      "caja": {
        "hombre": 402,
        "mujer": 280
      },
      "seguroPrivado": {
        "hombre": 203,
        "mujer": 131
      },
      "establecimientoPublico": {
        "hombre": 2369,
        "mujer": 2185
      },
      "establecimientoPrivado": {
        "hombre": 184,
        "mujer": 158
      },
      "medicoTradicional": {
        "hombre": 1068,
        "mujer": 946
      },
      "solucionCasera": {
        "hombre": 2715,
        "mujer": 2421
      },
      "farmacia": {
        "hombre": 801,
        "mujer": 661
      }
    },
    "ocupacion": {
      "agricultura": {
        "hombre": 1611,
        "mujer": 1337
      },
      "mineria": {
        "hombre": 291,
        "mujer": 11
      },
      "manufactura": {
        "hombre": 55,
        "mujer": 39
      },
      "electricidad": {
        "hombre": 1,
        "mujer": 0
      },
      "construccion": {
        "hombre": 144,
        "mujer": 10
      },
      "comercio": {
        "hombre": 188,
        "mujer": 163
      },
      "otrosServicios": {
        "hombre": 96,
        "mujer": 94
      },
      "sinEspecificar": {
        "hombre": 47,
        "mujer": 35
      },
      "descripcionIncompleta": {
        "hombre": 15,
        "mujer": 17
      }
    },
    "tipoEmpleo": {
      "obrero": {
        "hombre": 345,
        "mujer": 100
      },
      "trabajadorDelHogar": {
        "hombre": 0,
        "mujer": 10
      },
      "cuentaPropia": {
        "hombre": 1582,
        "mujer": 1189
      },
      "empleador": {
        "hombre": 45,
        "mujer": 20
      },
      "aprendiz": {
        "hombre": 107,
        "mujer": 81
      },
      "servicios": {
        "hombre": 6,
        "mujer": 0
      },
      "sinEspecificar": {
        "hombre": 363,
        "mujer": 306
      }
    }
  },
  "vivienda": {
    "particular": 1815,
    "colectiva": 28,
    "energia": {
      "tiene": 796,
      "noTiene": 899
    },
    "cocina": {
      "garrafa": 266,
      "gasDomiciliario": 0,
      "lena": 707,
      "otro": 714,
      "noCocina": 8
    },
    "agua": {
      "caneria": 650,
      "pilaPublica": 264,
      "carroRepartidor": 0,
      "pozo": 394,
      "rio": 365,
      "otro": 22
    },
    "desague": {
      "alcantarilla": 36,
      "camara": 41,
      "pozo": 160,
      "calle": 0,
      "rio": 4,
      "lago": 0
    },
    "basura": {
      "contenedor": 6,
      "carro": 4,
      "calle": 263,
      "rio": 874,
      "quema": 448,
      "entierro": 73,
      "otro": 27
    },
    "tics": {
      "radio": 1209,
      "television": 348,
      "computador": 23,
      "internet": 3,
      "celular": 395
    }
  }
}