{
  "depto": "CHUQUISACA",
  "prov": "TOMINA",
  "mun": "SOPACHUY",
  "poblacion": {
    "edades": {
      "edad0a3": {
        "hombre": 337,
        "mujer": 332
      },
      "edad4a5": {
        "hombre": 185,
        "mujer": 184
      },
      "edad6a19": {
        "hombre": 1190,
        "mujer": 1124
      },
      "edad20a39": {
        "hombre": 969,
        "mujer": 891
      },
      "edad40a59": {
        "hombre": 587,
        "mujer": 602
      },
      "edad60oMas": {
        "hombre": 406,
        "mujer": 505
      }
    },
    "mayorDeEdad": {
      "hombre": 2099,
      "mujer": 2092
    },
    "vivienda": {
      "particular": {
        "hombre": 3580,
        "mujer": 3590
      },
      "colectiva": {
        "hombre": 81,
        "mujer": 41
      },
      "movil": {
        "hombre": 12,
        "mujer": 7
      },
      "sinVivienda": {
        "hombre": 1,
        "mujer": 0
      }
    },
    "conCi": {
      "hombre": 2793,
      "mujer": 2739
    },
    "salud": {
      "caja": {
        "hombre": 247,
        "mujer": 309
      },
      "seguroPrivado": {
        "hombre": 86,
        "mujer": 81
      },
      "establecimientoPublico": {
        "hombre": 3072,
        "mujer": 3129
      },
      "establecimientoPrivado": {
        "hombre": 148,
        "mujer": 134
      },
      "medicoTradicional": {
        "hombre": 1719,
        "mujer": 1578
      },
      "solucionCasera": {
        "hombre": 2125,
        "mujer": 2138
      },
      "farmacia": {
        "hombre": 1077,
        "mujer": 1082
      }
    },
    "ocupacion": {
      "agricultura": {
        "hombre": 1488,
        "mujer": 325
      },
      "mineria": {
        "hombre": 1,
        "mujer": 0
      },
      "manufactura": {
        "hombre": 57,
        "mujer": 75
      },
      "electricidad": {
        "hombre": 2,
        "mujer": 0
      },
      "construccion": {
        "hombre": 189,
        "mujer": 3
      },
      "comercio": {
        "hombre": 132,
        "mujer": 125
      },
      "otrosServicios": {
        "hombre": 116,
        "mujer": 278
      },
      "sinEspecificar": {
        "hombre": 64,
        "mujer": 79
      },
      "descripcionIncompleta": {
        "hombre": 21,
        "mujer": 26
      }
    },
    "tipoEmpleo": {
      "obrero": {
        "hombre": 306,
        "mujer": 185
      },
      "trabajadorDelHogar": {
        "hombre": 0,
        "mujer": 24
      },
      "cuentaPropia": {
        "hombre": 1262,
        "mujer": 434
      },
      "empleador": {
        "hombre": 26,
        "mujer": 22
      },
      "aprendiz": {
        "hombre": 149,
        "mujer": 78
      },
      "servicios": {
        "hombre": 2,
        "mujer": 2
      },
      "sinEspecificar": {
        "hombre": 325,
        "mujer": 166
      }
    }
  },
  "vivienda": {
    "particular": 2612,
    "colectiva": 31,
    "energia": {
      "tiene": 800,
      "noTiene": 1210
    },
    "cocina": {
      "garrafa": 517,
      "gasDomiciliario": 0,
      "lena": 1455,
      "otro": 17,
      "noCocina": 21
    },
    "agua": {
      "caneria": 1080,
      "pilaPublica": 188,
      "carroRepartidor": 0,
      "pozo": 18,
      "rio": 707,
      "otro": 17
    },
    "desague": {
      "alcantarilla": 480,
      "camara": 10,
      "pozo": 162,
      "calle": 1,
      "rio": 5,
      "lago": 0
    },
    "basura": {
      "contenedor": 57,
      "carro": 500,
      "calle": 694,
      "rio": 124,
      "quema": 375,
      "entierro": 211,
      "otro": 49
    },
    "tics": {
      "radio": 1272,
      "television": 514,
      "computador": 148,
      "internet": 26,
      "celular": 589
    }
  }
}