{
  "depto": "POTOSí",
  "prov": "RAFAEL BUSTILLO",
  "mun": "",
  "poblacion": {
    "edades": {
      "edad0a3": {
        "hombre": 4218,
        "mujer": 3961
      },
      "edad4a5": {
        "hombre": 2076,
        "mujer": 1988
      },
      "edad6a19": {
        "hombre": 14429,
        "mujer": 14197
      },
      "edad20a39": {
        "hombre": 12140,
        "mujer": 12130
      },
      "edad40a59": {
        "hombre": 6768,
        "mujer": 7296
      },
      "edad60oMas": {
        "hombre": 3292,
        "mujer": 4777
      }
    },
    "mayorDeEdad": {
      "hombre": 23998,
      "mujer": 26064
    },
    "vivienda": {
      "particular": {
        "hombre": 42034,
        "mujer": 43744
      },
      "colectiva": {
        "hombre": 701,
        "mujer": 428
      },
      "movil": {
        "hombre": 110,
        "mujer": 103
      },
      "sinVivienda": {
        "hombre": 78,
        "mujer": 74
      }
    },
    "conCi": {
      "hombre": 32276,
      "mujer": 33924
    },
    "salud": {
      "caja": {
        "hombre": 11909,
        "mujer": 12492
      },
      "seguroPrivado": {
        "hombre": 2746,
        "mujer": 2897
      },
      "establecimientoPublico": {
        "hombre": 22557,
        "mujer": 24277
      },
      "establecimientoPrivado": {
        "hombre": 4428,
        "mujer": 4654
      },
      "medicoTradicional": {
        "hombre": 12704,
        "mujer": 12646
      },
      "solucionCasera": {
        "hombre": 23547,
        "mujer": 25100
      },
      "farmacia": {
        "hombre": 18389,
        "mujer": 19287
      }
    },
    "ocupacion": {
      "agricultura": {
        "hombre": 8235,
        "mujer": 7015
      },
      "mineria": {
        "hombre": 3434,
        "mujer": 208
      },
      "manufactura": {
        "hombre": 766,
        "mujer": 657
      },
      "electricidad": {
        "hombre": 44,
        "mujer": 10
      },
      "construccion": {
        "hombre": 2267,
        "mujer": 118
      },
      "comercio": {
        "hombre": 2267,
        "mujer": 2584
      },
      "otrosServicios": {
        "hombre": 2668,
        "mujer": 3501
      },
      "sinEspecificar": {
        "hombre": 848,
        "mujer": 983
      },
      "descripcionIncompleta": {
        "hombre": 340,
        "mujer": 300
      }
    },
    "tipoEmpleo": {
      "obrero": {
        "hombre": 4934,
        "mujer": 2656
      },
      "trabajadorDelHogar": {
        "hombre": 4,
        "mujer": 189
      },
      "cuentaPropia": {
        "hombre": 9847,
        "mujer": 7532
      },
      "empleador": {
        "hombre": 699,
        "mujer": 247
      },
      "aprendiz": {
        "hombre": 1104,
        "mujer": 1163
      },
      "servicios": {
        "hombre": 661,
        "mujer": 104
      },
      "sinEspecificar": {
        "hombre": 3620,
        "mujer": 3485
      }
    }
  },
  "vivienda": {
    "particular": 28824,
    "colectiva": 255,
    "energia": {
      "tiene": 20229,
      "noTiene": 5736
    },
    "cocina": {
      "garrafa": 16935,
      "gasDomiciliario": 0,
      "lena": 7791,
      "otro": 915,
      "noCocina": 324
    },
    "agua": {
      "caneria": 14923,
      "pilaPublica": 8069,
      "carroRepartidor": 243,
      "pozo": 1475,
      "rio": 1115,
      "otro": 140
    },
    "desague": {
      "alcantarilla": 8761,
      "camara": 400,
      "pozo": 1259,
      "calle": 34,
      "rio": 105,
      "lago": 4
    },
    "basura": {
      "contenedor": 1420,
      "carro": 10049,
      "calle": 1632,
      "rio": 9183,
      "quema": 2542,
      "entierro": 812,
      "otro": 327
    },
    "tics": {
      "radio": 19147,
      "television": 15148,
      "computador": 3928,
      "internet": 326,
      "celular": 13012
    }
  }
}