{
  "depto": "COCHABAMBA",
  "prov": "MIZQUE",
  "mun": "MIZQUE",
  "poblacion": {
    "edades": {
      "edad0a3": {
        "hombre": 1440,
        "mujer": 1367
      },
      "edad4a5": {
        "hombre": 713,
        "mujer": 752
      },
      "edad6a19": {
        "hombre": 4481,
        "mujer": 4362
      },
      "edad20a39": {
        "hombre": 3328,
        "mujer": 3315
      },
      "edad40a59": {
        "hombre": 2308,
        "mujer": 2241
      },
      "edad60oMas": {
        "hombre": 1164,
        "mujer": 1429
      }
    },
    "mayorDeEdad": {
      "hombre": 7465,
      "mujer": 7569
    },
    "vivienda": {
      "particular": {
        "hombre": 13323,
        "mujer": 13264
      },
      "colectiva": {
        "hombre": 82,
        "mujer": 193
      },
      "movil": {
        "hombre": 28,
        "mujer": 9
      },
      "sinVivienda": {
        "hombre": 1,
        "mujer": 0
      }
    },
    "conCi": {
      "hombre": 9248,
      "mujer": 9210
    },
    "salud": {
      "caja": {
        "hombre": 696,
        "mujer": 764
      },
      "seguroPrivado": {
        "hombre": 406,
        "mujer": 396
      },
      "establecimientoPublico": {
        "hombre": 9823,
        "mujer": 10156
      },
      "establecimientoPrivado": {
        "hombre": 1126,
        "mujer": 1195
      },
      "medicoTradicional": {
        "hombre": 4589,
        "mujer": 4617
      },
      "solucionCasera": {
        "hombre": 5706,
        "mujer": 5881
      },
      "farmacia": {
        "hombre": 4622,
        "mujer": 4586
      }
    },
    "ocupacion": {
      "agricultura": {
        "hombre": 5869,
        "mujer": 3779
      },
      "mineria": {
        "hombre": 627,
        "mujer": 36
      },
      "manufactura": {
        "hombre": 81,
        "mujer": 116
      },
      "electricidad": {
        "hombre": 3,
        "mujer": 0
      },
      "construccion": {
        "hombre": 438,
        "mujer": 15
      },
      "comercio": {
        "hombre": 333,
        "mujer": 393
      },
      "otrosServicios": {
        "hombre": 306,
        "mujer": 551
      },
      "sinEspecificar": {
        "hombre": 201,
        "mujer": 305
      },
      "descripcionIncompleta": {
        "hombre": 152,
        "mujer": 148
      }
    },
    "tipoEmpleo": {
      "obrero": {
        "hombre": 1049,
        "mujer": 536
      },
      "trabajadorDelHogar": {
        "hombre": 0,
        "mujer": 39
      },
      "cuentaPropia": {
        "hombre": 4893,
        "mujer": 2975
      },
      "empleador": {
        "hombre": 238,
        "mujer": 67
      },
      "aprendiz": {
        "hombre": 547,
        "mujer": 553
      },
      "servicios": {
        "hombre": 88,
        "mujer": 9
      },
      "sinEspecificar": {
        "hombre": 1195,
        "mujer": 1164
      }
    }
  },
  "vivienda": {
    "particular": 10640,
    "colectiva": 42,
    "energia": {
      "tiene": 4229,
      "noTiene": 3682
    },
    "cocina": {
      "garrafa": 2407,
      "gasDomiciliario": 0,
      "lena": 5406,
      "otro": 24,
      "noCocina": 74
    },
    "agua": {
      "caneria": 3273,
      "pilaPublica": 1100,
      "carroRepartidor": 7,
      "pozo": 267,
      "rio": 3020,
      "otro": 244
    },
    "desague": {
      "alcantarilla": 895,
      "camara": 142,
      "pozo": 339,
      "calle": 4,
      "rio": 75,
      "lago": 0
    },
    "basura": {
      "contenedor": 188,
      "carro": 1225,
      "calle": 2387,
      "rio": 1249,
      "quema": 2052,
      "entierro": 528,
      "otro": 282
    },
    "tics": {
      "radio": 5992,
      "television": 2766,
      "computador": 363,
      "internet": 52,
      "celular": 2893
    }
  }
}