{
  "depto": "POTOSí",
  "prov": "CHARCAS",
  "mun": "",
  "poblacion": {
    "edades": {
      "edad0a3": {
        "hombre": 2039,
        "mujer": 1989
      },
      "edad4a5": {
        "hombre": 1005,
        "mujer": 977
      },
      "edad6a19": {
        "hombre": 6911,
        "mujer": 6466
      },
      "edad20a39": {
        "hombre": 4799,
        "mujer": 4373
      },
      "edad40a59": {
        "hombre": 3662,
        "mujer": 3519
      },
      "edad60oMas": {
        "hombre": 2403,
        "mujer": 2739
      }
    },
    "mayorDeEdad": {
      "hombre": 11538,
      "mujer": 11255
    },
    "vivienda": {
      "particular": {
        "hombre": 20621,
        "mujer": 19909
      },
      "colectiva": {
        "hombre": 155,
        "mujer": 124
      },
      "movil": {
        "hombre": 37,
        "mujer": 28
      },
      "sinVivienda": {
        "hombre": 6,
        "mujer": 2
      }
    },
    "conCi": {
      "hombre": 13320,
      "mujer": 12058
    },
    "salud": {
      "caja": {
        "hombre": 1807,
        "mujer": 1693
      },
      "seguroPrivado": {
        "hombre": 295,
        "mujer": 336
      },
      "establecimientoPublico": {
        "hombre": 10982,
        "mujer": 11221
      },
      "establecimientoPrivado": {
        "hombre": 888,
        "mujer": 869
      },
      "medicoTradicional": {
        "hombre": 7895,
        "mujer": 7441
      },
      "solucionCasera": {
        "hombre": 11128,
        "mujer": 10697
      },
      "farmacia": {
        "hombre": 2704,
        "mujer": 2583
      }
    },
    "ocupacion": {
      "agricultura": {
        "hombre": 8364,
        "mujer": 5522
      },
      "mineria": {
        "hombre": 156,
        "mujer": 9
      },
      "manufactura": {
        "hombre": 110,
        "mujer": 273
      },
      "electricidad": {
        "hombre": 8,
        "mujer": 1
      },
      "construccion": {
        "hombre": 833,
        "mujer": 18
      },
      "comercio": {
        "hombre": 287,
        "mujer": 481
      },
      "otrosServicios": {
        "hombre": 579,
        "mujer": 766
      },
      "sinEspecificar": {
        "hombre": 599,
        "mujer": 683
      },
      "descripcionIncompleta": {
        "hombre": 108,
        "mujer": 142
      }
    },
    "tipoEmpleo": {
      "obrero": {
        "hombre": 1237,
        "mujer": 566
      },
      "trabajadorDelHogar": {
        "hombre": 0,
        "mujer": 100
      },
      "cuentaPropia": {
        "hombre": 5694,
        "mujer": 3825
      },
      "empleador": {
        "hombre": 158,
        "mujer": 78
      },
      "aprendiz": {
        "hombre": 928,
        "mujer": 727
      },
      "servicios": {
        "hombre": 65,
        "mujer": 70
      },
      "sinEspecificar": {
        "hombre": 2962,
        "mujer": 2529
      }
    }
  },
  "vivienda": {
    "particular": 13511,
    "colectiva": 100,
    "energia": {
      "tiene": 3101,
      "noTiene": 8687
    },
    "cocina": {
      "garrafa": 1496,
      "gasDomiciliario": 0,
      "lena": 9952,
      "otro": 286,
      "noCocina": 54
    },
    "agua": {
      "caneria": 3783,
      "pilaPublica": 3456,
      "carroRepartidor": 178,
      "pozo": 1058,
      "rio": 2956,
      "otro": 357
    },
    "desague": {
      "alcantarilla": 514,
      "camara": 284,
      "pozo": 535,
      "calle": 4,
      "rio": 17,
      "lago": 2
    },
    "basura": {
      "contenedor": 268,
      "carro": 630,
      "calle": 2747,
      "rio": 4288,
      "quema": 2632,
      "entierro": 852,
      "otro": 371
    },
    "tics": {
      "radio": 6805,
      "television": 1331,
      "computador": 352,
      "internet": 36,
      "celular": 1284
    }
  }
}